[
  {
    "symbol": "©",
    "id": "copy-to-register",
    "name": "Copy To Register",
    "arity": 1,
    "keywords": ["register"],
    "tags": ["register"],
    "tagline": "Save the result of a link to the <a href='/misc/register'>register</a> when it is called.",
    "description": "Given a link of any arity, return a link of the same arity that returns the exact same value. When it is run, the result is saved to the register.",
    "syntax": [["<link>©", "Modify <code>&lt;link&gt;</code> to save its result to the register"]]
  }
]
